help_tokens/__init__.py
help_tokens/apps.py
help_tokens/context_processor.py
help_tokens/core.py
help_tokens/models.py
help_tokens/urls.py
help_tokens/views.py
help_tokens-3.2.0.dist-info/licenses/AUTHORS
help_tokens-3.2.0.dist-info/licenses/LICENSE.txt
help_tokens-3.2.0.dist-info/METADATA
help_tokens-3.2.0.dist-info/WHEEL
help_tokens-3.2.0.dist-info/top_level.txt
help_tokens-3.2.0.dist-info/RECORD
